[
  {
    "keyword": "cartrack",
    "timestamp": "2026-07-01T09:49:37.844Z",
    "date": "2026/07/01",
    "time": "11:49",
    "month": "July 2026",
    "rank": 1,
    "volume": "34.9K",
    "difficulty": 20,
    "zaRank": 1,
    "topPage": "cartrack.co.za",
    "aiStatus": "included",
    "aiSnippet": "Cartrack offers real-time fleet tracking solutions...",
    "aiPlatforms": "5",
    "aiContext": "Strong AI visibility"
  },
  {
    "keyword": "cartrack",
    "timestamp": "2026-07-01T09:49:45.169Z",
    "date": "2026/07/01",
    "time": "11:49",
    "month": "July 2026",
    "rank": 2,
    "volume": "31.3K",
    "difficulty": 40,
    "zaRank": 1,
    "topPage": "cartrack.co.za",
    "aiStatus": "included",
    "aiSnippet": "Cartrack offers real-time fleet tracking solutions...",
    "aiPlatforms": "5",
    "aiContext": "Strong AI visibility"
  },
  {
    "keyword": "fleet management",
    "timestamp": "2026-07-01T09:50:35.792Z",
    "date": "2026/07/01",
    "time": "11:50",
    "month": "July 2026",
    "rank": 2,
    "volume": "22.7K",
    "difficulty": 32,
    "zaRank": 1,
    "topPage": "cartrack.co.za",
    "aiStatus": "included",
    "aiSnippet": "Cartrack offers real-time fleet tracking solutions...",
    "aiPlatforms": "5",
    "aiContext": "Strong AI visibility"
  },
  {
    "keyword": "cartrack",
    "timestamp": "2026-07-01T09:56:38.373Z",
    "date": "2026/07/01",
    "time": "11:56",
    "month": "July 2026",
    "rank": 7,
    "volume": "42.8K",
    "difficulty": 43,
    "zaRank": 1,
    "topPage": "cartrack.co.za",
    "aiStatus": "included",
    "aiSnippet": "Cartrack offers real-time fleet tracking solutions...",
    "aiPlatforms": "5",
    "aiContext": "Strong AI visibility"
  },
  {
    "keyword": "cartrack",
    "timestamp": "2026-07-01T09:57:02.676Z",
    "date": "2026/07/01",
    "time": "11:57",
    "month": "July 2026",
    "rank": 5,
    "volume": "28.4K",
    "difficulty": 63,
    "zaRank": 1,
    "topPage": "cartrack.co.za",
    "aiStatus": "included",
    "aiSnippet": "Cartrack offers real-time fleet tracking solutions...",
    "aiPlatforms": "5",
    "aiContext": "Strong AI visibility"
  },
  {
    "keyword": "fleet",
    "timestamp": "2026-07-01T09:57:17.711Z",
    "date": "2026/07/01",
    "time": "11:57",
    "month": "July 2026",
    "rank": 7,
    "volume": "9.2K",
    "difficulty": 21,
    "zaRank": 1,
    "topPage": "cartrack.co.za",
    "aiStatus": "included",
    "aiSnippet": "Cartrack offers real-time fleet tracking solutions...",
    "aiPlatforms": "5",
    "aiContext": "Strong AI visibility"
  },
  {
    "keyword": "cartrack",
    "timestamp": "2026-07-01T10:02:31.318Z",
    "date": "2026/07/01",
    "time": "12:02",
    "month": "July 2026",
    "rank": 8,
    "volume": "28.4K",
    "difficulty": 38,
    "zaRank": 1,
    "topPage": "cartrack.co.za",
    "aiStatus": "included",
    "aiSnippet": "Cartrack offers real-time fleet tracking solutions...",
    "aiPlatforms": "5",
    "aiContext": "Strong AI visibility"
  },
  {
    "keyword": "cartrack",
    "timestamp": "2026-07-01T10:10:10.198Z",
    "date": "2026/07/01",
    "time": "12:10",
    "month": "July 2026",
    "rank": 3,
    "volume": "35.7K",
    "difficulty": 31,
    "zaRank": 1,
    "topPage": "cartrack.co.za",
    "aiStatus": "included",
    "aiSnippet": "Cartrack offers real-time fleet tracking solutions...",
    "aiPlatforms": "5",
    "aiContext": "Strong AI visibility"
  },
  {
    "keyword": "vehicle tracking",
    "timestamp": "2026-07-01T10:10:18.123Z",
    "date": "2026/07/01",
    "time": "12:10",
    "month": "July 2026",
    "rank": 5,
    "volume": "14.9K",
    "difficulty": 37,
    "zaRank": 1,
    "topPage": "cartrack.co.za",
    "aiStatus": "included",
    "aiSnippet": "Cartrack offers real-time fleet tracking solutions...",
    "aiPlatforms": "5",
    "aiContext": "Strong AI visibility"
  }
]